tbr_deal_finder/__init__.py
tbr_deal_finder/__main__.py
tbr_deal_finder/book.py
tbr_deal_finder/cli.py
tbr_deal_finder/config.py
tbr_deal_finder/desktop_updater.py
tbr_deal_finder/migrations.py
tbr_deal_finder/owned_books.py
tbr_deal_finder/retailer_deal.py
tbr_deal_finder/tracked_books.py
tbr_deal_finder/utils.py
tbr_deal_finder/version_check.py
tbr_deal_finder/gui/__init__.py
tbr_deal_finder/gui/main.py
tbr_deal_finder/gui/pages/__init__.py
tbr_deal_finder/gui/pages/all_deals.py
tbr_deal_finder/gui/pages/base_book_page.py
tbr_deal_finder/gui/pages/base_deals_page.py
tbr_deal_finder/gui/pages/book_details.py
tbr_deal_finder/gui/pages/latest_deals.py
tbr_deal_finder/gui/pages/owned_books.py
tbr_deal_finder/gui/pages/settings.py
tbr_deal_finder/gui/pages/wishlist.py
tbr_deal_finder/queries/get_active_deals.sql
tbr_deal_finder/queries/get_deals_found_at.sql
tbr_deal_finder/queries/latest_deal_last_ran_most_recent_success.sql
tbr_deal_finder/queries/latest_unknown_book_sync.sql
tbr_deal_finder/retailer/__init__.py
tbr_deal_finder/retailer/amazon.py
tbr_deal_finder/retailer/amazon_custom_auth.py
tbr_deal_finder/retailer/audible.py
tbr_deal_finder/retailer/chirp.py
tbr_deal_finder/retailer/kindle.py
tbr_deal_finder/retailer/librofm.py
tbr_deal_finder/retailer/models.py
tbr_deal_finder-0.3.11.dist-info/METADATA
tbr_deal_finder-0.3.11.dist-info/WHEEL
tbr_deal_finder-0.3.11.dist-info/entry_points.txt
tbr_deal_finder-0.3.11.dist-info/licenses/LICENSE
tbr_deal_finder-0.3.11.dist-info/RECORD
