Metadata-Version: 2.4
Name: tbr-deal-finder
Version: 0.3.11
Summary: Track price drops and find deals on books in your TBR list across audiobook and ebook formats.
License: MIT
License-File: LICENSE
Requires-Python: >=3.13
Requires-Dist: aiocache>=0.12.3
Requires-Dist: aiohttp>=3.12.14
Requires-Dist: audible==0.8.2
Requires-Dist: click>=8.2.1
Requires-Dist: duckdb>=1.3.2
Requires-Dist: flet[all]==0.28.3
Requires-Dist: levenshtein>=0.27.1
Requires-Dist: pandas-stubs==2.3.0.250703
Requires-Dist: pandas>=2.3.1
Requires-Dist: plotly>=5.17.0
Requires-Dist: pyinstaller>=6.15.0
Requires-Dist: questionary>=2.1.0
Requires-Dist: tqdm>=4.67.1
Requires-Dist: unidecode>=1.4.0
